__init__.py
fsfa-0.2.2.dist-info/METADATA
fsfa-0.2.2.dist-info/WHEEL
fsfa-0.2.2.dist-info/entry_points.txt
fsfa-0.2.2.dist-info/licenses/LICENSE.txt
fsfa.py
fsfa-0.2.2.dist-info/RECORD
