Metadata-Version: 2.1
Name: fsfa
Version: 0.2.2
Summary: Feature-based Slow Feature Analysis
Author-Email: Kieran S Owens <kowe6911@uni.sydney.edu.au>
Maintainer-Email: Kieran S Owens <kowe6911@uni.sydney.edu.au>
Classifier: Programming Language :: Python :: 3
Classifier: Operating System :: OS Independent
Project-URL: GitHub Repository (fsfa), https://github.com/KieranOwens/fsfa
Requires-Python: >=3.8
Requires-Dist: numpy
Requires-Dist: pandas
Requires-Dist: pycatch22
Requires-Dist: sklearn-sfa
